ec_slp_lib.py
ec_slp_lib-1.1.0.dist-info/METADATA
ec_slp_lib-1.1.0.dist-info/WHEEL
ec_slp_lib-1.1.0.dist-info/RECORD
